organizations_local/__init__.py
organizations_local/organization.py
organizations_local/organizations_constants_src.py
organizations_local/organizations_local.py
organizations_local-0.0.56.dist-info/METADATA
organizations_local-0.0.56.dist-info/WHEEL
organizations_local-0.0.56.dist-info/top_level.txt
organizations_local-0.0.56.dist-info/RECORD
