Metadata-Version: 2.4
Name: organizations-local
Version: 0.0.56
Summary: PyPI Package for Circles organizations-local Python
Home-page: https://github.com/circles-zone/organizations-local-python-package
Author: Circles
Author-email: info@circlez.ai
Classifier: Programming Language :: Python :: 3
Classifier: Operating System :: OS Independent
Requires-Dist: database-mysql-local>=0.0.290
Requires-Dist: language-remote>=0.0.20
Requires-Dist: location-local>=0.0.8
Requires-Dist: user-context-remote>=0.0.58
Dynamic: author
Dynamic: author-email
Dynamic: classifier
Dynamic: description
Dynamic: description-content-type
Dynamic: home-page
Dynamic: requires-dist
Dynamic: summary
